HoloNet/__init__.py
HoloNet/_metadata.py
HoloNet/_setting.py
HoloNet/colorSchemes.py
HoloNet/plotting/CE_plotting.py
HoloNet/plotting/MGC_for_multi_target_interpretation_plotting.py
HoloNet/plotting/MGC_interpretation_plotting.py
HoloNet/plotting/MGC_performance_plotting.py
HoloNet/plotting/__init__.py
HoloNet/plotting/base_plot.py
HoloNet/plotting/hyperparameter_plotting.py
HoloNet/plotting/lr_clustering_plotting.py
HoloNet/predicting/MGC_for_multi_target.py
HoloNet/predicting/MGC_model.py
HoloNet/predicting/MGC_training.py
HoloNet/predicting/__init__.py
HoloNet/predicting/input_preprocessing.py
HoloNet/predicting/model_saving_loading.py
HoloNet/predicting/target_preprocessing.py
HoloNet/preprocessing/__init__.py
HoloNet/preprocessing/adata_loading.py
HoloNet/preprocessing/lr_database_preprocessing.py
HoloNet/tools/CE_network_centrality.py
HoloNet/tools/CE_network_edge_filtering.py
HoloNet/tools/CE_network_edge_weighting.py
HoloNet/tools/__init__.py
HoloNet/tools/hyperparameter_selecting.py
HoloNet/tools/lr_clustering_based_on_CE_network.py
HoloNet-0.1.0.dist-info/LICENSE
HoloNet-0.1.0.dist-info/METADATA
HoloNet-0.1.0.dist-info/WHEEL
HoloNet-0.1.0.dist-info/top_level.txt
HoloNet-0.1.0.dist-info/RECORD
